mtgcolors/__init__.py
mtgcolors/core.py
mtgcolors/helpers.py
mtgcolors-0.1.0a20190815120833.dist-info/LICENSE.txt
mtgcolors-0.1.0a20190815120833.dist-info/METADATA
mtgcolors-0.1.0a20190815120833.dist-info/WHEEL
mtgcolors-0.1.0a20190815120833.dist-info/top_level.txt
mtgcolors-0.1.0a20190815120833.dist-info/RECORD
