Metadata-Version: 2.1
Name: mtgcolors
Version: 0.1.0a20190815120833
Summary: MtgColors is module to detail mtg colors
Home-page: https://gitlab.com/aloisdegouvello/mtgcolors
Author: aloisdg
Author-email: aloisdg@protonmail.com
License: UNKNOWN
Platform: UNKNOWN
Classifier: Programming Language :: Python :: 3
Classifier: License :: OSI Approved :: GNU General Public License v3 or later (GPLv3+)
Classifier: Operating System :: OS Independent
